mpeg1fs.py
mpeg1fs-0.0.2.dist-info/LICENSE
mpeg1fs-0.0.2.dist-info/METADATA
mpeg1fs-0.0.2.dist-info/WHEEL
mpeg1fs-0.0.2.dist-info/entry_points.txt
mpeg1fs-0.0.2.dist-info/top_level.txt
mpeg1fs-0.0.2.dist-info/RECORD
