Metadata-Version: 2.2
Name: mpeg1fs
Version: 0.0.2
Summary: A FUSE FS that transcodes to MPEG1
Author-email: Tim Felgentreff <timfelgentreff@gmail.com>
Maintainer-email: Tim Felgentreff <timfelgentreff@gmail.com>
License: AGPL-3.0-or-later
Project-URL: Repository, https://github.com/timfel/mpeg1fs.git
Project-URL: Issues, https://github.com/timfel/issues
Requires-Python: >=3.10
License-File: LICENSE
Requires-Dist: fusepy>=3.0.1
Requires-Dist: yt-dlp>=2025
Provides-Extra: dev
Requires-Dist: black>=22.3.0; extra == "dev"
